[
  {
    "full_name": "CrowCpp/Crow",
    "stargazers_count": 645,
    "open_issues_count": 18,
    "forks_count": 80
  },
  {
    "full_name": "godotengine/godot",
    "stargazers_count": 45619,
    "open_issues_count": 6932,
    "forks_count": 8223
  },
  {
    "full_name": "godotengine/godot",
    "stargazers_count": 45619,
    "open_issues_count": 6932,
    "forks_count": 8223
  },
  {
    "full_name": "godotengine/godot",
    "stargazers_count": 45619,
    "open_issues_count": 6932,
    "forks_count": 8223
  },
  {
    "full_name": "lirios/text",
    "stargazers_count": 72,
    "open_issues_count": 15,
    "forks_count": 21
  },
  {
    "full_name": "lirios/text",
    "stargazers_count": 72,
    "open_issues_count": 15,
    "forks_count": 21
  },
  {
    "full_name": "GNOME/meld",
    "stargazers_count": 744,
    "open_issues_count": 0,
    "forks_count": 201
  },
  {
    "full_name": "GNOME/meld",
    "stargazers_count": 744,
    "open_issues_count": 0,
    "forks_count": 201
  }
]