[
  {
    "full_name": "CrowCpp/Crow",
    "stargazers_count": 939,
    "open_issues_count": 34,
    "forks_count": 107
  },
  {
    "full_name": "godotengine/godot",
    "stargazers_count": 48526,
    "open_issues_count": 7564,
    "forks_count": 8684
  },
  {
    "full_name": "godotengine/godot",
    "stargazers_count": 48526,
    "open_issues_count": 7564,
    "forks_count": 8684
  },
  {
    "full_name": "godotengine/godot",
    "stargazers_count": 48526,
    "open_issues_count": 7564,
    "forks_count": 8684
  },
  {
    "full_name": "lirios/text",
    "stargazers_count": 76,
    "open_issues_count": 15,
    "forks_count": 21
  },
  {
    "full_name": "lirios/text",
    "stargazers_count": 76,
    "open_issues_count": 15,
    "forks_count": 21
  },
  {
    "full_name": "GNOME/meld",
    "stargazers_count": 767,
    "open_issues_count": 0,
    "forks_count": 208
  },
  {
    "full_name": "GNOME/meld",
    "stargazers_count": 767,
    "open_issues_count": 0,
    "forks_count": 208
  }
]